skt7
