Metadata-Version: 1.0
Name: skt7
Version: 0.2.1
Summary: Library for api of all my python codes
Home-page: https://github.com/skt7/python-skt
Author: SKT
Author-email: developerskt@gmail.com
License: MIT
Platform: UNKNOWN
